tagil/__init__.py
tagil/application.py
tagil/decorators.py
tagil/exceptions.py
tagil/manager.py
tagil/singleton.py
tagil-0.2.0.dist-info/METADATA
tagil-0.2.0.dist-info/WHEEL
tagil-0.2.0.dist-info/RECORD
