Metadata-Version: 2.1
Name: tagil
Version: 0.2.0
Summary: Dependency injection library for python
License: MIT
Author: Kirill Sulim
Author-email: kirillsulim@gmail.com
Requires-Python: >=3.8,<4.0
Classifier: License :: OSI Approved :: MIT License
Classifier: Programming Language :: Python :: 3
Classifier: Programming Language :: Python :: 3.8
Classifier: Programming Language :: Python :: 3.9
Classifier: Programming Language :: Python :: 3.10
Classifier: Programming Language :: Python :: 3.11
Project-URL: repository, https://github.com/kirillsulim/tagil
